tokenette/__init__.py
tokenette/cli.py
tokenette/config.py
tokenette/server.py
tokenette/core/__init__.py
tokenette/core/amplifier.py
tokenette/core/cache.py
tokenette/core/compressor.py
tokenette/core/minifier.py
tokenette/core/optimizer.py
tokenette/core/router.py
tokenette/tools/__init__.py
tokenette/tools/analysis.py
tokenette/tools/context7.py
tokenette/tools/file_ops.py
tokenette/tools/git_ops.py
tokenette/tools/meta.py
tokenette/tools/prompts.py
tokenette/tools/tokens.py
tokenette/tools/workspace.py
tokenette-2.0.0.dist-info/METADATA
tokenette-2.0.0.dist-info/WHEEL
tokenette-2.0.0.dist-info/entry_points.txt
tokenette-2.0.0.dist-info/licenses/LICENSE
tokenette-2.0.0.dist-info/RECORD
