Metadata-Version: 2.4
Name: tokenette
Version: 2.0.0
Summary: The Ultimate All-in-One AI Coding Enhancement MCP - Zero-Loss Token Optimization · Intelligent Model Routing · Quality Amplification
Project-URL: Homepage, https://github.com/itsmeadarsh2008/tokenette
Project-URL: Documentation, https://tokenette.dev
Project-URL: Repository, https://github.com/itsmeadarsh2008/tokenette
Project-URL: Issues, https://github.com/itsmeadarsh2008/tokenette/issues
Author-email: Adarsh Gourab Mahalik <adarshgourabmahalik@outlook.com>
License-Expression: MIT
License-File: LICENSE
Keywords: ai-coding,claude,copilot,fastmcp,llm,mcp,model-context-protocol,token-optimization
Classifier: Development Status :: 4 - Beta
Classifier: Intended Audience :: Developers
Classifier: License :: OSI Approved :: MIT License
Classifier: Programming Language :: Python :: 3
Classifier: Programming Language :: Python :: 3.11
Classifier: Programming Language :: Python :: 3.12
Classifier: Programming Language :: Python :: 3.13
Classifier: Topic :: Scientific/Engineering :: Artificial Intelligence
Classifier: Topic :: Software Development :: Libraries :: Python Modules
Requires-Python: >=3.11
Requires-Dist: aiofiles>=24.0.0
Requires-Dist: cachetools>=5.3.0
Requires-Dist: diskcache>=5.6.0
Requires-Dist: fastmcp>=2.0.0
Requires-Dist: httpx>=0.27.0
Requires-Dist: orjson>=3.9.0
Requires-Dist: pydantic>=2.0.0
Requires-Dist: python-dotenv>=1.0.0
Requires-Dist: rich>=13.7.0
Requires-Dist: typer>=0.12.0
Requires-Dist: watchfiles>=0.21.0
Requires-Dist: xxhash>=3.4.0
Provides-Extra: dev
Requires-Dist: mypy>=1.9.0; extra == 'dev'
Requires-Dist: pre-commit>=3.6.0; extra == 'dev'
Requires-Dist: pytest-asyncio>=0.23.0; extra == 'dev'
Requires-Dist: pytest-cov>=4.1.0; extra == 'dev'
Requires-Dist: pytest>=8.0.0; extra == 'dev'
Requires-Dist: ruff>=0.3.0; extra == 'dev'
Requires-Dist: twine>=5.0.0; extra == 'dev'
Provides-Extra: full
Requires-Dist: mypy>=1.9.0; extra == 'full'
Requires-Dist: numpy>=1.26.0; extra == 'full'
Requires-Dist: pre-commit>=3.6.0; extra == 'full'
Requires-Dist: pytest-asyncio>=0.23.0; extra == 'full'
Requires-Dist: pytest-cov>=4.1.0; extra == 'full'
Requires-Dist: pytest>=8.0.0; extra == 'full'
Requires-Dist: ruff>=0.3.0; extra == 'full'
Requires-Dist: sentence-transformers>=2.5.0; extra == 'full'
Requires-Dist: twine>=5.0.0; extra == 'full'
Provides-Extra: vector
Requires-Dist: numpy>=1.26.0; extra == 'vector'
Requires-Dist: sentence-transformers>=2.5.0; extra == 'vector'
